awslabs/__init__.py
awslabs/healthlake_mcp_server/__init__.py
awslabs/healthlake_mcp_server/fhir_operations.py
awslabs/healthlake_mcp_server/main.py
awslabs/healthlake_mcp_server/models.py
awslabs/healthlake_mcp_server/server.py
awslabs_healthlake_mcp_server-0.0.8.dist-info/METADATA
awslabs_healthlake_mcp_server-0.0.8.dist-info/WHEEL
awslabs_healthlake_mcp_server-0.0.8.dist-info/entry_points.txt
awslabs_healthlake_mcp_server-0.0.8.dist-info/licenses/LICENSE
awslabs_healthlake_mcp_server-0.0.8.dist-info/licenses/NOTICE
awslabs_healthlake_mcp_server-0.0.8.dist-info/RECORD
